__init__.py
nearest_advocate.py
nearest_advocate_cython.py
nearest_advocate_numba.py
nearest_advocate_python.py
setup.py
archive/nearest_advocate_c.pyx
archive/nearest_advocate_c_int64.pyx
nearest_advocate-0.2.0.5.dist-info/licenses/LICENSE
nearest_advocate-0.2.0.5.dist-info/METADATA
nearest_advocate-0.2.0.5.dist-info/WHEEL
nearest_advocate-0.2.0.5.dist-info/top_level.txt
nearest_advocate-0.2.0.5.dist-info/RECORD
