Metadata-Version: 2.4
Name: nearest_advocate
Version: 0.2.0.5
Summary: A time delay estimation method for discrete event-based time-series data.
Author-email: Christoph Schranz <christoph.schranz@salzburgresearch.at>, Mathias Schmoigl-Tonis <mathias.schmoigl-tonis@salzburgresearch.at>
Project-URL: Homepage, https://github.com/iot-salzburg/nearest-advocate
Project-URL: Bug Tracker, https://github.com/iot-salzburg/nearest-advocate/issues
Classifier: Programming Language :: Python :: 3
Classifier: License :: OSI Approved :: MIT License
Classifier: Operating System :: OS Independent
Requires-Python: >=3.6
License-File: LICENSE
Dynamic: license-file
